cig_data_extractor/__init__.py
cig_data_extractor/_version.py
cig_data_extractor/get_cig_data_requests.py
cig_data_extractor-0.2.4.dist-info/METADATA
cig_data_extractor-0.2.4.dist-info/WHEEL
cig_data_extractor-0.2.4.dist-info/entry_points.txt
cig_data_extractor-0.2.4.dist-info/top_level.txt
cig_data_extractor-0.2.4.dist-info/RECORD
