Metadata-Version: 2.4
Name: cig-data-extractor
Version: 0.2.4
Summary: A tool to extract CIG data
Author-email: Andrea Borruso <aborruso@gmail.com>
Classifier: Programming Language :: Python :: 3
Classifier: License :: OSI Approved :: MIT License
Classifier: Operating System :: OS Independent
Requires-Python: >=3.7
Requires-Dist: requests
